{"result":{"stories":[{"inappropriateContentFlaggers":[],"editedAt":{"__type":"Date","iso":"2018-03-08T23:31:43.397Z"},"searchTerms":["1","b","bo","boy","boyf","boyfr","boyfri","boyfrie","boyfrien","boyfriend","c","cl","cls","clst","clsto","clston","clstone","e","ep","epi","epis","episo","episod","episode","f","fa","fak","fake","m","my","s","st","sto","ston","stone"],"tags":[""],"authors":[{"__type":"Pointer","className":"Author","objectId":"TEKMJMEKyI"}],"characters":[{"__type":"Pointer","className":"Character","objectId":"iUKAnpDDn5"},{"__type":"Pointer","className":"Character","objectId":"hpWDOrk9u8"}],"authorsObjectIds":["XcKlOeE3he"],"uid":"thenewgirl-1-myfakeboyfriend","hidden":false,"title":"My Fake Boyfriend - Episode 1","seriesTitle":"My Fake Boyfriend","lang":"en","canonicalTitle":"my fake boyfriend","storyDescription":"Hazel gets teased by all the boys, but Jack has a secret crush on her…","trackMessage":false,"editorsChoice":false,"createdOutsideApp":true,"creator":"web-uploader","pendingDeletion":false,"inappropriateContent":false,"seriesTitleAutoGenerated":true,"alreadyPublished":true,"risk":6,"wordCount":965,"seriesIdentifier":"0b6b22f3-6d4b-55fd-942a-9653736c8412","category":{"__type":"Pointer","className":"Genre","objectId":"PE8id6J1mi"},"episodeIndex":1,"episodeSeriesName":"Episode 1","episodeTitle":"Episode 1","episodeCount":10,"author":{"autoFolloweesFollowers":[],"username":"CLStone","lastName":"Stone","firstName":"C.L.","fullName":"C.L. Stone","bio":"C. L. Stone likes 🍫 and #findingburiedtreasure. Her books are about 💞 and @dark_themes and #chocolatechippancakes.","profilePictureSmall":{"__type":"File","name":"cbd6628c68064ce76288ae3ae6ecd336_224-small.jpg","url":"https://d3b7s6bg6ueiky.cloudfront.net/cbd6628c68064ce76288ae3ae6ecd336_224-small.jpg"},"profilePictureMedium":{"__type":"File","name":"184ae0bdaaa84c8ac4d69822098612ae_224-medium.jpg","url":"https://d3b7s6bg6ueiky.cloudfront.net/184ae0bdaaa84c8ac4d69822098612ae_224-medium.jpg"},"createdAt":"2017-11-16T20:12:34.814Z","updatedAt":"2018-06-13T20:21:09.883Z","usernameUpdatedAt":{"__type":"Date","iso":"2017-11-16T20:12:34.923Z"},"canonicalUsername":"clstone","writeCount":10,"lastUpdateMetrics":{"__type":"Date","iso":"2018-03-12T14:28:00.232Z"},"followerCount":18,"followingCount":14,"loveCount":0,"readCount":0,"writtenStoryReadingRightsUntil":{"__type":"Date","iso":"2018-11-28T09:44:24.725Z"},"lastNotificationCreatedAt":{"__type":"Date","iso":"2018-06-13T20:21:09.868Z"},"bestSellingBadgeType":"nyt","ACL":{"*":{"read":true},"XcKlOeE3he":{"read":true,"write":true}},"objectId":"XcKlOeE3he","__type":"Object","className":"_User"},"coverImageThumbnailFile":{"__type":"File","name":"d70a2f0718a3eff9644ed58e220f8466_4358-thumbnail.jpg","url":"https://d3b7s6bg6ueiky.cloudfront.net/d70a2f0718a3eff9644ed58e220f8466_4358-thumbnail.jpg"},"coverImageLoRes":{"__type":"File","name":"ffe88c40ded0dc0b49920cbf4089faa6_4358-thumbnail-lores.jpg","url":"https://d3b7s6bg6ueiky.cloudfront.net/ffe88c40ded0dc0b49920cbf4089faa6_4358-thumbnail-lores.jpg"},"coverImageFile":{"__type":"File","name":"de8d20109fd6cb7fdbbcfe115bce09ae_4358.jpg","url":"https://d3b7s6bg6ueiky.cloudfront.net/de8d20109fd6cb7fdbbcfe115bce09ae_4358.jpg"},"recommendable":true,"searchable":true,"readable":true,"country":"en","createdAt":"2017-11-17T18:18:54.906Z","updatedAt":"2018-07-04T05:21:29.493Z","aclUpdatedAt":{"__type":"Date","iso":"2017-11-17T18:18:54.941Z"},"completionRate_android":14.291808873720136,"seriesAverageCompletionRate_ios":77.9205484637547,"seriesAverageCompletionRate_android":9.975594341484374,"seriesAverageCompletionRate":31.86034027579036,"lastUpdateMetrics":{"__type":"Date","iso":"2018-07-03T08:42:05.734Z"},"sampleLovers":[],"readCount":27261,"previousReadVelocity":235,"readVelocity":233,"readAcceleration":-2,"searchTermsUpdatedAt":{"__type":"Date","iso":"2018-07-04T03:11:00.969Z"},"riskUpdatedAt":{"__type":"Date","iso":"2017-12-12T05:26:08.759Z"},"authorPromoURL":null,"authorPromoDescription":null,"authorPromoCTA":null,"authorPromoImage":null,"completed_ios":22347,"loveRatio":0.005025494295880562,"i18n":"fr,es,de,ja,ko,pt,it,ar","seriesCompletionRate":16.04153802975021,"started_ios":44550,"group":4,"seriesCompletionRate_ios":27.333348301488584,"teaserVideoUrl":"http://dvgf17xr8ms83.cloudfront.net/SWPbMm9iRm/video_5a1b8c054de2b.mov","completionRate_ios":50.1605334650531,"completionRate":32.226775189447096,"commentCount":29,"sentimentAverage":2.291666666666667,"sentimentCount":24,"started_android":44543,"completed_android":6365,"loveCount":137,"seriesCompletionRate_android":4.748967127716903,"rd_started_ios":12557,"rd_started_android":26566,"rd_completed_ios":6528,"rd_completed_android":1795,"rd_completionRate_android":6.756756756756757,"scoreUpdatedAt":{"__type":"Date","iso":"2018-07-04T05:09:00.201Z"},"completionRateUpdatedAt":{"__type":"Date","iso":"2018-07-04T04:30:06.888Z"},"commentRatio":0.0010725248714819335,"metascore":40.813896606370925,"teaser":false,"genre":"Romance","style":"{\"theme\":\"imessage\",\"messages\":{\"characterColors\":[\"#E5CF9F\",\"#A8E7E1\"],\"textColors\":[\"#000000\",\"#000000\"]}}","postPaywallNotification":"Aww! Did Hazel just ask Jack to be her fake boyfriend? Tap back into Hooked to see what he says 😍😍","rd_completionRate_ios":51.98693955562634,"ACL":{"*":{"read":true},"XcKlOeE3he":{"write":true}},"objectId":"SWPbMm9iRm","__type":"Object","className":"Story"},{"inappropriateContentFlaggers":[],"editedAt":{"__type":"Date","iso":"2018-03-08T23:31:56.923Z"},"searchTerms":["2","b","bo","boy","boyf","boyfr","boyfri","boyfrie","boyfrien","boyfriend","c","cl","cls","clst","clsto","clston","clstone","e","ep","epi","epis","episo","episod","episode","f","fa","fak","fake","m","my","s","st","sto","ston","stone"],"tags":[""],"authors":[{"__type":"Pointer","className":"Author","objectId":"TEKMJMEKyI"}],"characters":[{"__type":"Pointer","className":"Character","objectId":"B4UjQy6pE1"},{"__type":"Pointer","className":"Character","objectId":"uHSmysHgC2"},{"__type":"Pointer","className":"Character","objectId":"V9crqIVnh9"}],"authorsObjectIds":["XcKlOeE3he"],"uid":"myfakeboyfriend-2","hidden":false,"title":"My Fake Boyfriend - Episode 2","seriesTitle":"My Fake Boyfriend","lang":"en","canonicalTitle":"my fake boyfriend","storyDescription":"Hazel gets teased by all the boys, but Jack has a secret crush on her…","trackMessage":false,"editorsChoice":false,"teaser":false,"createdOutsideApp":true,"creator":"web-uploader","pendingDeletion":false,"inappropriateContent":false,"seriesTitleAutoGenerated":true,"alreadyPublished":true,"risk":-1,"wordCount":903,"seriesIdentifier":"0b6b22f3-6d4b-55fd-942a-9653736c8412","category":{"__type":"Pointer","className":"Genre","objectId":"PE8id6J1mi"},"episodeIndex":2,"episodeSeriesName":"Episode 2","episodeTitle":"Episode 2","episodeCount":10,"author":{"autoFolloweesFollowers":[],"username":"CLStone","lastName":"Stone","firstName":"C.L.","fullName":"C.L. Stone","bio":"C. L. Stone likes 🍫 and #findingburiedtreasure. Her books are about 💞 and @dark_themes and #chocolatechippancakes.","profilePictureSmall":{"__type":"File","name":"cbd6628c68064ce76288ae3ae6ecd336_224-small.jpg","url":"https://d3b7s6bg6ueiky.cloudfront.net/cbd6628c68064ce76288ae3ae6ecd336_224-small.jpg"},"profilePictureMedium":{"__type":"File","name":"184ae0bdaaa84c8ac4d69822098612ae_224-medium.jpg","url":"https://d3b7s6bg6ueiky.cloudfront.net/184ae0bdaaa84c8ac4d69822098612ae_224-medium.jpg"},"createdAt":"2017-11-16T20:12:34.814Z","updatedAt":"2018-06-13T20:21:09.883Z","usernameUpdatedAt":{"__type":"Date","iso":"2017-11-16T20:12:34.923Z"},"canonicalUsername":"clstone","writeCount":10,"lastUpdateMetrics":{"__type":"Date","iso":"2018-03-12T14:28:00.232Z"},"followerCount":18,"followingCount":14,"loveCount":0,"readCount":0,"writtenStoryReadingRightsUntil":{"__type":"Date","iso":"2018-11-28T09:44:24.725Z"},"lastNotificationCreatedAt":{"__type":"Date","iso":"2018-06-13T20:21:09.868Z"},"bestSellingBadgeType":"nyt","ACL":{"*":{"read":true},"XcKlOeE3he":{"read":true,"write":true}},"objectId":"XcKlOeE3he","__type":"Object","className":"_User"},"recommendable":false,"searchable":true,"readable":true,"country":"en","genre":"Romance","group":1,"createdAt":"2018-03-02T22:31:50.065Z","updatedAt":"2018-07-04T05:10:21.548Z","aclUpdatedAt":{"__type":"Date","iso":"2018-03-02T22:31:50.100Z"},"searchTermsUpdatedAt":{"__type":"Date","iso":"2018-07-04T04:44:01.007Z"},"lastUpdateMetrics":{"__type":"Date","iso":"2018-07-03T08:48:06.614Z"},"sampleLovers":[],"readCount":23765,"scoreUpdatedAt":{"__type":"Date","iso":"2018-07-04T05:09:00.201Z"},"previousReadVelocity":184,"readVelocity":183,"readAcceleration":-1,"i18n":"fr,es,de,ja,ko,pt,it,ar","style":"{\"theme\":\"imessage\",\"messages\":{\"characterColors\":[\"#CED699\",\"#A8E7E1\",\"#E5CF9F\"],\"textColors\":[\"#000000\",\"#000000\",\"#000000\"]}}","started_ios":26493,"completed_ios":18989,"loveRatio":0.003366294971596886,"coverImageFile":{"__type":"File","name":"5c09a96aa26b483496d2f34ffd4ac490_myfakeboyfriend_cover_v3.jpg","url":"https://d3b7s6bg6ueiky.cloudfront.net/5c09a96aa26b483496d2f34ffd4ac490_myfakeboyfriend_cover_v3.jpg"},"prePaywallNotification":"OMG Jack and Hazel are SO cute—but can their “fake relationship” last? Tap back into Hooked to find out.","postPaywallNotification":"Did Jack just admit that he wants to kiss Hazel for real? 😘😘 Tap back into Hooked to see how she responds.","commentRatio":0.0004661807085946771,"completionRateUpdatedAt":{"__type":"Date","iso":"2018-07-04T04:30:06.888Z"},"rd_started_ios":6226,"rd_started_android":31067,"rd_completed_ios":5217,"rd_completed_android":1378,"completionRate_ios":71.68585992070983,"completionRate_android":11.725193435932319,"rd_completionRate_ios":83.79376806938645,"rd_completionRate_android":4.435574725593073,"completionRate":33.32290660827701,"seriesAverageCompletionRate_ios":77.9205484637547,"seriesAverageCompletionRate_android":9.975594341484374,"seriesAverageCompletionRate":31.86034027579036,"seriesCompletionRate_ios":27.333348301488584,"seriesCompletionRate_android":4.748967127716903,"seriesCompletionRate":16.04153802975021,"started_android":47044,"completed_android":5516,"loveCount":80,"commentCount":11,"sentimentAverage":2.1,"sentimentCount":10,"metascore":39.491063200983646,"ACL":{"*":{"read":true},"XcKlOeE3he":{"write":true}},"objectId":"B1wmkfB5uw","__type":"Object","className":"Story"},{"inappropriateContentFlaggers":[],"editedAt":{"__type":"Date","iso":"2018-03-08T23:32:34.103Z"},"searchTerms":["3","b","bo","boy","boyf","boyfr","boyfri","boyfrie","boyfrien","boyfriend","c","cl","cls","clst","clsto","clston","clstone","e","ep","epi","epis","episo","episod","episode","f","fa","fak","fake","m","my","s","st","sto","ston","stone"],"tags":[""],"authors":[{"__type":"Pointer","className":"Author","objectId":"TEKMJMEKyI"}],"characters":[{"__type":"Pointer","className":"Character","objectId":"gAGYQdFfHS"},{"__type":"Pointer","className":"Character","objectId":"yK7eC1WhPs"},{"__type":"Pointer","className":"Character","objectId":"8fFX6xbnoG"},{"__type":"Pointer","className":"Character","objectId":"BJOUOSg5Xy"}],"authorsObjectIds":["XcKlOeE3he"],"uid":"myfakeboyfriend-3","hidden":false,"title":"My Fake Boyfriend - Episode 3","seriesTitle":"My Fake Boyfriend","lang":"en","canonicalTitle":"my fake boyfriend","storyDescription":"Hazel gets teased by all the boys, but Jack has a secret crush on her…","trackMessage":false,"editorsChoice":false,"teaser":false,"createdOutsideApp":true,"creator":"web-uploader","pendingDeletion":false,"inappropriateContent":false,"seriesTitleAutoGenerated":true,"alreadyPublished":true,"risk":-1,"wordCount":867,"seriesIdentifier":"0b6b22f3-6d4b-55fd-942a-9653736c8412","category":{"__type":"Pointer","className":"Genre","objectId":"PE8id6J1mi"},"episodeIndex":3,"episodeSeriesName":"Episode 3","episodeTitle":"Episode 3","episodeCount":10,"author":{"autoFolloweesFollowers":[],"username":"CLStone","lastName":"Stone","firstName":"C.L.","fullName":"C.L. Stone","bio":"C. L. Stone likes 🍫 and #findingburiedtreasure. Her books are about 💞 and @dark_themes and #chocolatechippancakes.","profilePictureSmall":{"__type":"File","name":"cbd6628c68064ce76288ae3ae6ecd336_224-small.jpg","url":"https://d3b7s6bg6ueiky.cloudfront.net/cbd6628c68064ce76288ae3ae6ecd336_224-small.jpg"},"profilePictureMedium":{"__type":"File","name":"184ae0bdaaa84c8ac4d69822098612ae_224-medium.jpg","url":"https://d3b7s6bg6ueiky.cloudfront.net/184ae0bdaaa84c8ac4d69822098612ae_224-medium.jpg"},"createdAt":"2017-11-16T20:12:34.814Z","updatedAt":"2018-06-13T20:21:09.883Z","usernameUpdatedAt":{"__type":"Date","iso":"2017-11-16T20:12:34.923Z"},"canonicalUsername":"clstone","writeCount":10,"lastUpdateMetrics":{"__type":"Date","iso":"2018-03-12T14:28:00.232Z"},"followerCount":18,"followingCount":14,"loveCount":0,"readCount":0,"writtenStoryReadingRightsUntil":{"__type":"Date","iso":"2018-11-28T09:44:24.725Z"},"lastNotificationCreatedAt":{"__type":"Date","iso":"2018-06-13T20:21:09.868Z"},"bestSellingBadgeType":"nyt","ACL":{"*":{"read":true},"XcKlOeE3he":{"read":true,"write":true}},"objectId":"XcKlOeE3he","__type":"Object","className":"_User"},"recommendable":false,"searchable":true,"readable":true,"country":"en","genre":"Romance","group":2,"createdAt":"2018-03-02T22:33:11.707Z","updatedAt":"2018-07-04T05:23:34.287Z","aclUpdatedAt":{"__type":"Date","iso":"2018-03-02T22:33:11.770Z"},"lastUpdateMetrics":{"__type":"Date","iso":"2018-07-03T08:48:06.134Z"},"sampleLovers":[],"readCount":21218,"scoreUpdatedAt":{"__type":"Date","iso":"2018-07-04T05:05:00.119Z"},"previousReadVelocity":175,"readVelocity":176,"readAcceleration":1,"searchTermsUpdatedAt":{"__type":"Date","iso":"2018-07-04T04:44:01.021Z"},"i18n":"fr,es,de,ja,ko,pt,it,ar","style":"{\"theme\":\"imessage\",\"messages\":{\"characterColors\":[\"#F1ADAC\",\"#A8E7E1\",\"#E5CF9F\",\"#CED699\"],\"textColors\":[\"#000000\",\"#000000\",\"#000000\",\"#000000\"]}}","started_ios":19382,"coverImageFile":{"__type":"File","name":"1a38ee0fd14f09fec8daabb49ce2cef2_myfakeboyfriend_cover_v3.jpg","url":"https://d3b7s6bg6ueiky.cloudfront.net/1a38ee0fd14f09fec8daabb49ce2cef2_myfakeboyfriend_cover_v3.jpg"},"prePaywallNotification":"Oh no! 😱 Mike is trying to bully Hazel into getting into his car. Tap back into Hooked to see if Jack gets back in time.","postPaywallNotification":"Ooh—want to see what Jack got Hazel? Tap back into Hooked!","completed_ios":16870,"loveRatio":0.0034404750683382033,"commentRatio":0.0005699088145896656,"completionRateUpdatedAt":{"__type":"Date","iso":"2018-07-04T04:30:06.888Z"},"rd_started_ios":5314,"rd_started_android":36914,"rd_completed_ios":4772,"rd_completed_android":1244,"completionRate_ios":87.03101615317128,"completionRate_android":9.318449564495259,"rd_completionRate_ios":89.80052691004893,"rd_completionRate_android":3.3699951238012678,"completionRate":30.480915172297486,"seriesAverageCompletionRate_ios":77.9205484637547,"seriesAverageCompletionRate_android":9.975594341484374,"seriesAverageCompletionRate":31.86034027579036,"seriesCompletionRate_ios":27.333348301488584,"seriesCompletionRate_android":4.748967127716903,"seriesCompletionRate":16.04153802975021,"started_android":51779,"completed_android":4828,"loveCount":73,"commentCount":12,"sentimentAverage":2.2,"sentimentCount":10,"metascore":39.061770311148166,"ACL":{"*":{"read":true},"XcKlOeE3he":{"write":true}},"objectId":"jAjU7Hxhzg","__type":"Object","className":"Story"},{"inappropriateContentFlaggers":[],"editedAt":{"__type":"Date","iso":"2018-03-08T23:32:47.596Z"},"searchTerms":["4","b","bo","boy","boyf","boyfr","boyfri","boyfrie","boyfrien","boyfriend","c","cl","cls","clst","clsto","clston","clstone","e","ep","epi","epis","episo","episod","episode","f","fa","fak","fake","m","my","s","st","sto","ston","stone"],"tags":[""],"authors":[{"__type":"Pointer","className":"Author","objectId":"TEKMJMEKyI"}],"characters":[{"__type":"Pointer","className":"Character","objectId":"PS0CNHnQTb"},{"__type":"Pointer","className":"Character","objectId":"NpWjj8NBeU"},{"__type":"Pointer","className":"Character","objectId":"iqUZdWv0fo"}],"authorsObjectIds":["XcKlOeE3he"],"uid":"myfakeboyfriend-4","hidden":false,"title":"My Fake Boyfriend - Episode 4","seriesTitle":"My Fake Boyfriend","lang":"en","canonicalTitle":"my fake boyfriend","storyDescription":"Hazel gets teased by all the boys, but Jack has a secret crush on her…","trackMessage":false,"editorsChoice":false,"teaser":false,"createdOutsideApp":true,"creator":"web-uploader","pendingDeletion":false,"inappropriateContent":false,"seriesTitleAutoGenerated":true,"alreadyPublished":true,"risk":-1,"wordCount":657,"seriesIdentifier":"0b6b22f3-6d4b-55fd-942a-9653736c8412","category":{"__type":"Pointer","className":"Genre","objectId":"PE8id6J1mi"},"episodeIndex":4,"episodeSeriesName":"Episode 4","episodeTitle":"Episode 4","episodeCount":10,"author":{"autoFolloweesFollowers":[],"username":"CLStone","lastName":"Stone","firstName":"C.L.","fullName":"C.L. Stone","bio":"C. L. Stone likes 🍫 and #findingburiedtreasure. Her books are about 💞 and @dark_themes and #chocolatechippancakes.","profilePictureSmall":{"__type":"File","name":"cbd6628c68064ce76288ae3ae6ecd336_224-small.jpg","url":"https://d3b7s6bg6ueiky.cloudfront.net/cbd6628c68064ce76288ae3ae6ecd336_224-small.jpg"},"profilePictureMedium":{"__type":"File","name":"184ae0bdaaa84c8ac4d69822098612ae_224-medium.jpg","url":"https://d3b7s6bg6ueiky.cloudfront.net/184ae0bdaaa84c8ac4d69822098612ae_224-medium.jpg"},"createdAt":"2017-11-16T20:12:34.814Z","updatedAt":"2018-06-13T20:21:09.883Z","usernameUpdatedAt":{"__type":"Date","iso":"2017-11-16T20:12:34.923Z"},"canonicalUsername":"clstone","writeCount":10,"lastUpdateMetrics":{"__type":"Date","iso":"2018-03-12T14:28:00.232Z"},"followerCount":18,"followingCount":14,"loveCount":0,"readCount":0,"writtenStoryReadingRightsUntil":{"__type":"Date","iso":"2018-11-28T09:44:24.725Z"},"lastNotificationCreatedAt":{"__type":"Date","iso":"2018-06-13T20:21:09.868Z"},"bestSellingBadgeType":"nyt","ACL":{"*":{"read":true},"XcKlOeE3he":{"read":true,"write":true}},"objectId":"XcKlOeE3he","__type":"Object","className":"_User"},"recommendable":false,"searchable":true,"readable":true,"country":"en","group":4,"createdAt":"2018-03-02T22:34:18.403Z","updatedAt":"2018-07-04T05:05:06.665Z","aclUpdatedAt":{"__type":"Date","iso":"2018-03-02T22:34:18.521Z"},"lastUpdateMetrics":{"__type":"Date","iso":"2018-07-03T08:45:05.753Z"},"sampleLovers":[],"readCount":19216,"scoreUpdatedAt":{"__type":"Date","iso":"2018-07-04T05:05:00.119Z"},"previousReadVelocity":166,"readVelocity":167,"readAcceleration":1,"searchTermsUpdatedAt":{"__type":"Date","iso":"2018-07-04T04:44:01.022Z"},"i18n":"fr,es,de,ja,ko,pt,it,ar","style":"{\"theme\":\"imessage\",\"messages\":{\"characterColors\":[\"#A8E7E1\",\"#CED699\",\"#F1ADAC\"],\"textColors\":[\"#000000\",\"#000000\",\"#000000\"]}}","coverImageFile":{"__type":"File","name":"5a489f26acff0fad98b475bde31a1a01_myfakeboyfriend_cover_v3.jpg","url":"https://d3b7s6bg6ueiky.cloudfront.net/5a489f26acff0fad98b475bde31a1a01_myfakeboyfriend_cover_v3.jpg"},"postPaywallNotification":"Oh no! Are Jack and Hazel going to get caught for faking their relationship? Tap back into Hooked to find out.","prePaywallNotification":"Will Jack ever tell Hazel how he really feels? Tap back into Hooked to find out.","genre":"Romance","started_ios":17202,"completed_ios":15323,"loveRatio":0.0031744379683597,"commentRatio":0.000367049446804048,"completionRateUpdatedAt":{"__type":"Date","iso":"2018-07-04T04:30:06.888Z"},"rd_started_ios":4827,"rd_started_android":22246,"rd_completed_ios":4418,"rd_completed_android":1110,"completionRate_ios":89.08921716877981,"completionRate_android":13.259340315773018,"rd_completionRate_ios":91.52682825771701,"rd_completionRate_android":4.98966106266295,"completionRate":39.77104048475976,"seriesAverageCompletionRate_ios":77.9205484637547,"seriesAverageCompletionRate_android":9.975594341484374,"seriesAverageCompletionRate":31.86034027579036,"seriesCompletionRate_ios":27.333348301488584,"seriesCompletionRate_android":4.748967127716903,"seriesCompletionRate":16.04153802975021,"started_android":31988,"completed_android":4241,"loveCount":61,"commentCount":7,"sentimentAverage":2,"sentimentCount":6,"metascore":37.79819348529013,"ACL":{"*":{"read":true},"XcKlOeE3he":{"write":true}},"objectId":"1LYqBHTA7U","__type":"Object","className":"Story"},{"inappropriateContentFlaggers":[],"editedAt":{"__type":"Date","iso":"2018-03-13T00:04:21.918Z"},"searchTerms":["5","b","bo","boy","boyf","boyfr","boyfri","boyfrie","boyfrien","boyfriend","c","cl","cls","clst","clsto","clston","clstone","e","ep","epi","epis","episo","episod","episode","f","fa","fak","fake","m","my","s","st","sto","ston","stone"],"tags":[""],"authors":[{"__type":"Pointer","className":"Author","objectId":"TEKMJMEKyI"}],"characters":[{"__type":"Pointer","className":"Character","objectId":"vAiQ0BUyYi"},{"__type":"Pointer","className":"Character","objectId":"TjPqSM1ZIa"},{"__type":"Pointer","className":"Character","objectId":"NEUNvJS7fu"}],"authorsObjectIds":["XcKlOeE3he"],"uid":"myfakeboyfriend-5","hidden":false,"title":"My Fake Boyfriend - Episode 5","seriesTitle":"My Fake Boyfriend","lang":"en","canonicalTitle":"my fake boyfriend","storyDescription":"Hazel gets teased by all the boys, but Jack has a secret crush on her…","trackMessage":false,"editorsChoice":false,"teaser":false,"createdOutsideApp":true,"creator":"web-uploader","pendingDeletion":false,"inappropriateContent":false,"seriesTitleAutoGenerated":true,"alreadyPublished":true,"risk":-1,"wordCount":795,"seriesIdentifier":"0b6b22f3-6d4b-55fd-942a-9653736c8412","category":{"__type":"Pointer","className":"Genre","objectId":"PE8id6J1mi"},"episodeIndex":5,"episodeSeriesName":"Episode 5","episodeTitle":"Episode 5","episodeCount":10,"author":{"autoFolloweesFollowers":[],"username":"CLStone","lastName":"Stone","firstName":"C.L.","fullName":"C.L. Stone","bio":"C. L. Stone likes 🍫 and #findingburiedtreasure. Her books are about 💞 and @dark_themes and #chocolatechippancakes.","profilePictureSmall":{"__type":"File","name":"cbd6628c68064ce76288ae3ae6ecd336_224-small.jpg","url":"https://d3b7s6bg6ueiky.cloudfront.net/cbd6628c68064ce76288ae3ae6ecd336_224-small.jpg"},"profilePictureMedium":{"__type":"File","name":"184ae0bdaaa84c8ac4d69822098612ae_224-medium.jpg","url":"https://d3b7s6bg6ueiky.cloudfront.net/184ae0bdaaa84c8ac4d69822098612ae_224-medium.jpg"},"createdAt":"2017-11-16T20:12:34.814Z","updatedAt":"2018-06-13T20:21:09.883Z","usernameUpdatedAt":{"__type":"Date","iso":"2017-11-16T20:12:34.923Z"},"canonicalUsername":"clstone","writeCount":10,"lastUpdateMetrics":{"__type":"Date","iso":"2018-03-12T14:28:00.232Z"},"followerCount":18,"followingCount":14,"loveCount":0,"readCount":0,"writtenStoryReadingRightsUntil":{"__type":"Date","iso":"2018-11-28T09:44:24.725Z"},"lastNotificationCreatedAt":{"__type":"Date","iso":"2018-06-13T20:21:09.868Z"},"bestSellingBadgeType":"nyt","ACL":{"*":{"read":true},"XcKlOeE3he":{"read":true,"write":true}},"objectId":"XcKlOeE3he","__type":"Object","className":"_User"},"recommendable":false,"searchable":true,"readable":true,"country":"en","genre":"Romance","group":2,"createdAt":"2018-03-02T22:35:14.310Z","updatedAt":"2018-07-04T05:12:22.271Z","aclUpdatedAt":{"__type":"Date","iso":"2018-03-02T22:35:14.345Z"},"lastUpdateMetrics":{"__type":"Date","iso":"2018-07-03T08:45:05.675Z"},"sampleLovers":[],"readCount":17671,"scoreUpdatedAt":{"__type":"Date","iso":"2018-07-04T05:05:00.119Z"},"previousReadVelocity":166,"readVelocity":162,"readAcceleration":-4,"searchTermsUpdatedAt":{"__type":"Date","iso":"2018-07-04T04:44:01.026Z"},"i18n":"fr,es,de,ja,ko,pt,it,ar","style":"{\"theme\":\"imessage\",\"messages\":{\"characterColors\":[\"#E5CF9F\",\"#A8E7E1\",\"#CED699\"],\"textColors\":[\"#000000\",\"#000000\",\"#000000\"]}}","coverImageFile":{"__type":"File","name":"1ecb067d3fb2948a7170450405e62e97_myfakeboyfriend_cover_v3.jpg","url":"https://d3b7s6bg6ueiky.cloudfront.net/1ecb067d3fb2948a7170450405e62e97_myfakeboyfriend_cover_v3.jpg"},"postPaywallNotification":"What will Jack choose? Tap back into Hooked to see of he breaks up with Hazel—or makes their relationship real 💗","prePaywallNotification":"Why does Mike need to ruin everything between Hazel and Jack? Tap back into Hooked to see if their feelings for each other can rise above him 💞","started_ios":15764,"loveRatio":0.0036217531548865373,"completed_ios":14051,"commentRatio":0.00039933823948884705,"completionRateUpdatedAt":{"__type":"Date","iso":"2018-07-04T04:30:06.888Z"},"rd_started_ios":4457,"rd_started_android":25825,"rd_completed_ios":4113,"rd_completed_android":1022,"completionRate_ios":89.13636652071833,"completionRate_android":10.813233605064852,"rd_completionRate_ios":92.28180390397128,"rd_completionRate_android":3.957405614714424,"completionRate":34.80060634328358,"seriesAverageCompletionRate_ios":77.9205484637547,"seriesAverageCompletionRate_android":9.975594341484374,"seriesAverageCompletionRate":31.86034027579036,"seriesCompletionRate_ios":27.333348301488584,"seriesCompletionRate_android":4.748967127716903,"seriesCompletionRate":16.04153802975021,"started_android":35697,"completed_android":3861,"loveCount":64,"commentCount":7,"sentimentAverage":2.4,"sentimentCount":5,"metascore":39.555602164694136,"ACL":{"*":{"read":true},"XcKlOeE3he":{"write":true}},"objectId":"n7sApADKhY","__type":"Object","className":"Story"},{"inappropriateContentFlaggers":[],"editedAt":{"__type":"Date","iso":"2018-03-08T23:33:05.394Z"},"searchTerms":["6","b","bo","boy","boyf","boyfr","boyfri","boyfrie","boyfrien","boyfriend","c","cl","cls","clst","clsto","clston","clstone","e","ep","epi","epis","episo","episod","episode","f","fa","fak","fake","m","my","s","st","sto","ston","stone"],"tags":[""],"authors":[{"__type":"Pointer","className":"Author","objectId":"TEKMJMEKyI"}],"characters":[{"__type":"Pointer","className":"Character","objectId":"YfTE58d8yo"},{"__type":"Pointer","className":"Character","objectId":"6EA7tVInF5"},{"__type":"Pointer","className":"Character","objectId":"BMKTDNdKoI"}],"authorsObjectIds":["XcKlOeE3he"],"uid":"myfakeboyfriend-6","hidden":false,"title":"My Fake Boyfriend - Episode 6","seriesTitle":"My Fake Boyfriend","lang":"en","canonicalTitle":"my fake boyfriend","storyDescription":"Hazel gets teased by all the boys, but Jack has a secret crush on her…","trackMessage":false,"editorsChoice":false,"teaser":false,"createdOutsideApp":true,"creator":"web-uploader","pendingDeletion":false,"inappropriateContent":false,"seriesTitleAutoGenerated":true,"alreadyPublished":true,"risk":-1,"wordCount":1172,"seriesIdentifier":"0b6b22f3-6d4b-55fd-942a-9653736c8412","category":{"__type":"Pointer","className":"Genre","objectId":"PE8id6J1mi"},"episodeIndex":6,"episodeSeriesName":"Episode 6","episodeTitle":"Episode 6","episodeCount":10,"author":{"autoFolloweesFollowers":[],"username":"CLStone","lastName":"Stone","firstName":"C.L.","fullName":"C.L. Stone","bio":"C. L. Stone likes 🍫 and #findingburiedtreasure. Her books are about 💞 and @dark_themes and #chocolatechippancakes.","profilePictureSmall":{"__type":"File","name":"cbd6628c68064ce76288ae3ae6ecd336_224-small.jpg","url":"https://d3b7s6bg6ueiky.cloudfront.net/cbd6628c68064ce76288ae3ae6ecd336_224-small.jpg"},"profilePictureMedium":{"__type":"File","name":"184ae0bdaaa84c8ac4d69822098612ae_224-medium.jpg","url":"https://d3b7s6bg6ueiky.cloudfront.net/184ae0bdaaa84c8ac4d69822098612ae_224-medium.jpg"},"createdAt":"2017-11-16T20:12:34.814Z","updatedAt":"2018-06-13T20:21:09.883Z","usernameUpdatedAt":{"__type":"Date","iso":"2017-11-16T20:12:34.923Z"},"canonicalUsername":"clstone","writeCount":10,"lastUpdateMetrics":{"__type":"Date","iso":"2018-03-12T14:28:00.232Z"},"followerCount":18,"followingCount":14,"loveCount":0,"readCount":0,"writtenStoryReadingRightsUntil":{"__type":"Date","iso":"2018-11-28T09:44:24.725Z"},"lastNotificationCreatedAt":{"__type":"Date","iso":"2018-06-13T20:21:09.868Z"},"bestSellingBadgeType":"nyt","ACL":{"*":{"read":true},"XcKlOeE3he":{"read":true,"write":true}},"objectId":"XcKlOeE3he","__type":"Object","className":"_User"},"recommendable":false,"searchable":true,"readable":true,"country":"en","genre":"Romance","group":1,"createdAt":"2018-03-02T22:36:39.063Z","updatedAt":"2018-07-04T05:23:04.323Z","aclUpdatedAt":{"__type":"Date","iso":"2018-03-02T22:36:39.098Z"},"scoreUpdatedAt":{"__type":"Date","iso":"2018-07-04T05:05:00.119Z"},"previousReadVelocity":156,"readVelocity":155,"readAcceleration":-1,"lastUpdateMetrics":{"__type":"Date","iso":"2018-07-03T08:42:05.408Z"},"sampleLovers":[],"readCount":16093,"searchTermsUpdatedAt":{"__type":"Date","iso":"2018-07-04T04:44:01.027Z"},"i18n":"fr,es,de,ja,ko,pt,it,ar","style":"{\"theme\":\"imessage\",\"messages\":{\"characterColors\":[\"#A8E7E1\",\"#E5CF9F\",\"#EDAFCD\"],\"textColors\":[\"#000000\",\"#000000\",\"#000000\"]}}","coverImageFile":{"__type":"File","name":"80c60c4da4c6f7b774d21176f2f71635_myfakeboyfriend_cover_v3.jpg","url":"https://d3b7s6bg6ueiky.cloudfront.net/80c60c4da4c6f7b774d21176f2f71635_myfakeboyfriend_cover_v3.jpg"},"postPaywallNotification":"Poor Hazel always gets picked on! At least she was lucky to find Jack 🍀 Tap back into Hooked to see how he comforts her.","prePaywallNotification":"Can’t wait to see the morning date between Jack and Hazel?? Then Tap back into Hooked.","started_ios":14483,"completed_ios":12821,"loveRatio":0.003417634996582365,"commentRatio":0.00037612838515546637,"completionRateUpdatedAt":{"__type":"Date","iso":"2018-07-04T04:30:06.888Z"},"rd_started_ios":4189,"rd_started_android":36829,"rd_completed_ios":3772,"rd_completed_android":910,"completionRate_ios":88.50749361143725,"completionRate_android":7.01885421292745,"rd_completionRate_ios":90.04535688708522,"rd_completionRate_android":2.4708789269325804,"completionRate":25.449489979224268,"seriesAverageCompletionRate_ios":77.9205484637547,"seriesAverageCompletionRate_android":9.975594341484374,"seriesAverageCompletionRate":31.86034027579036,"seriesCompletionRate_ios":27.333348301488584,"seriesCompletionRate_android":4.748967127716903,"seriesCompletionRate":16.04153802975021,"started_android":49539,"completed_android":3477,"loveCount":55,"commentCount":6,"sentimentAverage":2.4,"sentimentCount":5,"metascore":38.329550586890534,"ACL":{"*":{"read":true},"XcKlOeE3he":{"write":true}},"objectId":"BxNIsxMxaP","__type":"Object","className":"Story"},{"inappropriateContentFlaggers":[],"editedAt":{"__type":"Date","iso":"2018-03-08T23:33:12.035Z"},"searchTerms":["7","b","bo","boy","boyf","boyfr","boyfri","boyfrie","boyfrien","boyfriend","c","cl","cls","clst","clsto","clston","clstone","e","ep","epi","epis","episo","episod","episode","f","fa","fak","fake","m","my","s","st","sto","ston","stone"],"tags":[""],"authors":[{"__type":"Pointer","className":"Author","objectId":"TEKMJMEKyI"}],"characters":[{"__type":"Pointer","className":"Character","objectId":"JehgKZ5Zv0"},{"__type":"Pointer","className":"Character","objectId":"nCUSuddUHJ"},{"__type":"Pointer","className":"Character","objectId":"ht987oaoGq"}],"authorsObjectIds":["XcKlOeE3he"],"uid":"myfakeboyfriend-7","hidden":false,"title":"My Fake Boyfriend - Episode 7","seriesTitle":"My Fake Boyfriend","lang":"en","canonicalTitle":"my fake boyfriend","storyDescription":"Hazel gets teased by all the boys, but Jack has a secret crush on her…","trackMessage":false,"editorsChoice":false,"teaser":false,"createdOutsideApp":true,"creator":"web-uploader","pendingDeletion":false,"inappropriateContent":false,"seriesTitleAutoGenerated":true,"alreadyPublished":true,"risk":-1,"wordCount":737,"seriesIdentifier":"0b6b22f3-6d4b-55fd-942a-9653736c8412","category":{"__type":"Pointer","className":"Genre","objectId":"PE8id6J1mi"},"episodeIndex":7,"episodeSeriesName":"Episode 7","episodeTitle":"Episode 7","episodeCount":10,"author":{"autoFolloweesFollowers":[],"username":"CLStone","lastName":"Stone","firstName":"C.L.","fullName":"C.L. Stone","bio":"C. L. Stone likes 🍫 and #findingburiedtreasure. Her books are about 💞 and @dark_themes and #chocolatechippancakes.","profilePictureSmall":{"__type":"File","name":"cbd6628c68064ce76288ae3ae6ecd336_224-small.jpg","url":"https://d3b7s6bg6ueiky.cloudfront.net/cbd6628c68064ce76288ae3ae6ecd336_224-small.jpg"},"profilePictureMedium":{"__type":"File","name":"184ae0bdaaa84c8ac4d69822098612ae_224-medium.jpg","url":"https://d3b7s6bg6ueiky.cloudfront.net/184ae0bdaaa84c8ac4d69822098612ae_224-medium.jpg"},"createdAt":"2017-11-16T20:12:34.814Z","updatedAt":"2018-06-13T20:21:09.883Z","usernameUpdatedAt":{"__type":"Date","iso":"2017-11-16T20:12:34.923Z"},"canonicalUsername":"clstone","writeCount":10,"lastUpdateMetrics":{"__type":"Date","iso":"2018-03-12T14:28:00.232Z"},"followerCount":18,"followingCount":14,"loveCount":0,"readCount":0,"writtenStoryReadingRightsUntil":{"__type":"Date","iso":"2018-11-28T09:44:24.725Z"},"lastNotificationCreatedAt":{"__type":"Date","iso":"2018-06-13T20:21:09.868Z"},"bestSellingBadgeType":"nyt","ACL":{"*":{"read":true},"XcKlOeE3he":{"read":true,"write":true}},"objectId":"XcKlOeE3he","__type":"Object","className":"_User"},"recommendable":false,"searchable":true,"readable":true,"country":"en","genre":"Romance","group":1,"createdAt":"2018-03-02T22:37:49.282Z","updatedAt":"2018-07-04T05:24:06.039Z","aclUpdatedAt":{"__type":"Date","iso":"2018-03-02T22:37:49.323Z"},"lastUpdateMetrics":{"__type":"Date","iso":"2018-07-03T08:45:06.239Z"},"sampleLovers":[],"readCount":15377,"scoreUpdatedAt":{"__type":"Date","iso":"2018-07-04T05:05:00.119Z"},"previousReadVelocity":155,"readVelocity":154,"readAcceleration":-1,"searchTermsUpdatedAt":{"__type":"Date","iso":"2018-07-04T04:44:01.034Z"},"i18n":"fr,es,de,ja,ko,pt,it,ar","style":"{\"theme\":\"imessage\",\"messages\":{\"characterColors\":[\"#E5CF9F\",\"#A8E7E1\",\"#F1ADAC\"],\"textColors\":[\"#000000\",\"#000000\",\"#000000\"]}}","coverImageFile":{"__type":"File","name":"5f3b5edce6c41a82a0322b01f7c14cbe_myfakeboyfriend_cover_v3.jpg","url":"https://d3b7s6bg6ueiky.cloudfront.net/5f3b5edce6c41a82a0322b01f7c14cbe_myfakeboyfriend_cover_v3.jpg"},"postPaywallNotification":"Shoot—Mike is cornering Hazel again! Tap into Hooked to see if Jack gets back in time to save her.","prePaywallNotification":"Uh-oh…Is Jack going to spill that it’s a “her” and not a “him” who’s gotten him interested in going to college? Tap back into Hooked to find out.","started_ios":13027,"completed_ios":12233,"loveRatio":0.0033816739285946543,"commentRatio":0.00039377830281551486,"completionRateUpdatedAt":{"__type":"Date","iso":"2018-07-04T04:30:06.888Z"},"rd_started_ios":3828,"rd_started_android":24450,"rd_completed_ios":3640,"rd_completed_android":878,"completionRate_ios":93.93241167434716,"completionRate_android":9.889352004557859,"rd_completionRate_ios":95.08881922675026,"rd_completionRate_android":3.591002044989775,"completionRate":33.48789061657573,"seriesAverageCompletionRate_ios":77.9205484637547,"seriesAverageCompletionRate_android":9.975594341484374,"seriesAverageCompletionRate":31.86034027579036,"seriesCompletionRate_ios":27.333348301488584,"seriesCompletionRate_android":4.748967127716903,"seriesCompletionRate":16.04153802975021,"started_android":33349,"completed_android":3299,"loveCount":52,"commentCount":6,"sentimentAverage":2.6666666666666665,"sentimentCount":6,"metascore":40.220966111793054,"ACL":{"*":{"read":true},"XcKlOeE3he":{"write":true}},"objectId":"kr5uUHKfUc","__type":"Object","className":"Story"},{"inappropriateContentFlaggers":[],"editedAt":{"__type":"Date","iso":"2018-03-08T23:33:20.023Z"},"searchTerms":["8","b","bo","boy","boyf","boyfr","boyfri","boyfrie","boyfrien","boyfriend","c","cl","cls","clst","clsto","clston","clstone","e","ep","epi","epis","episo","episod","episode","f","fa","fak","fake","m","my","s","st","sto","ston","stone"],"tags":[""],"authors":[{"__type":"Pointer","className":"Author","objectId":"TEKMJMEKyI"}],"characters":[{"__type":"Pointer","className":"Character","objectId":"BtHqo5gCpF"},{"__type":"Pointer","className":"Character","objectId":"VdsKJwGnY0"}],"authorsObjectIds":["XcKlOeE3he"],"uid":"myfakeboyfriend-8","hidden":false,"title":"My Fake Boyfriend - Episode 8","seriesTitle":"My Fake Boyfriend","lang":"en","canonicalTitle":"my fake boyfriend","storyDescription":"Hazel gets teased by all the boys, but Jack has a secret crush on her…","trackMessage":false,"editorsChoice":false,"teaser":false,"createdOutsideApp":true,"creator":"web-uploader","pendingDeletion":false,"inappropriateContent":false,"seriesTitleAutoGenerated":true,"alreadyPublished":true,"risk":-1,"wordCount":586,"seriesIdentifier":"0b6b22f3-6d4b-55fd-942a-9653736c8412","category":{"__type":"Pointer","className":"Genre","objectId":"PE8id6J1mi"},"episodeIndex":8,"episodeSeriesName":"Episode 8","episodeTitle":"Episode 8","episodeCount":10,"author":{"autoFolloweesFollowers":[],"username":"CLStone","lastName":"Stone","firstName":"C.L.","fullName":"C.L. Stone","bio":"C. L. Stone likes 🍫 and #findingburiedtreasure. Her books are about 💞 and @dark_themes and #chocolatechippancakes.","profilePictureSmall":{"__type":"File","name":"cbd6628c68064ce76288ae3ae6ecd336_224-small.jpg","url":"https://d3b7s6bg6ueiky.cloudfront.net/cbd6628c68064ce76288ae3ae6ecd336_224-small.jpg"},"profilePictureMedium":{"__type":"File","name":"184ae0bdaaa84c8ac4d69822098612ae_224-medium.jpg","url":"https://d3b7s6bg6ueiky.cloudfront.net/184ae0bdaaa84c8ac4d69822098612ae_224-medium.jpg"},"createdAt":"2017-11-16T20:12:34.814Z","updatedAt":"2018-06-13T20:21:09.883Z","usernameUpdatedAt":{"__type":"Date","iso":"2017-11-16T20:12:34.923Z"},"canonicalUsername":"clstone","writeCount":10,"lastUpdateMetrics":{"__type":"Date","iso":"2018-03-12T14:28:00.232Z"},"followerCount":18,"followingCount":14,"loveCount":0,"readCount":0,"writtenStoryReadingRightsUntil":{"__type":"Date","iso":"2018-11-28T09:44:24.725Z"},"lastNotificationCreatedAt":{"__type":"Date","iso":"2018-06-13T20:21:09.868Z"},"bestSellingBadgeType":"nyt","ACL":{"*":{"read":true},"XcKlOeE3he":{"read":true,"write":true}},"objectId":"XcKlOeE3he","__type":"Object","className":"_User"},"recommendable":false,"searchable":true,"readable":true,"country":"en","genre":"Romance","group":4,"createdAt":"2018-03-02T22:39:34.155Z","updatedAt":"2018-07-04T05:05:06.629Z","aclUpdatedAt":{"__type":"Date","iso":"2018-03-02T22:39:34.201Z"},"scoreUpdatedAt":{"__type":"Date","iso":"2018-07-04T05:05:00.119Z"},"previousReadVelocity":145,"readVelocity":145,"readAcceleration":0,"lastUpdateMetrics":{"__type":"Date","iso":"2018-07-03T08:42:05.695Z"},"sampleLovers":[],"readCount":14902,"searchTermsUpdatedAt":{"__type":"Date","iso":"2018-07-04T04:55:00.909Z"},"i18n":"fr,es,de,ja,ko,pt,it,ar","style":"{\"theme\":\"imessage\",\"messages\":{\"characterColors\":[\"#A8E7E1\",\"#E5CF9F\"],\"textColors\":[\"#000000\",\"#000000\"]}}","coverImageFile":{"__type":"File","name":"f442114839df822798883ec78da68a45_myfakeboyfriend_cover_v3.jpg","url":"https://d3b7s6bg6ueiky.cloudfront.net/f442114839df822798883ec78da68a45_myfakeboyfriend_cover_v3.jpg"},"postPaywallNotification":"😱 Oh no! Did Jack just end things with Hazel? Tap back into Hooked to see how she responds.","prePaywallNotification":"Is Jack seriously hurt? Tap back into Hooked to find out.","started_ios":12500,"loveRatio":0.0034223594148436454,"completed_ios":11863,"commentRatio":0.0006093845216331506,"completionRateUpdatedAt":{"__type":"Date","iso":"2018-07-04T04:30:06.888Z"},"rd_started_ios":3723,"rd_started_android":19378,"rd_completed_ios":3564,"rd_completed_android":849,"completionRate_ios":94.8943661971831,"completionRate_android":12.067051934632017,"rd_completionRate_ios":95.72925060435134,"rd_completionRate_android":4.381257095675508,"completionRate":38.86343042071197,"seriesAverageCompletionRate_ios":77.9205484637547,"seriesAverageCompletionRate_android":9.975594341484374,"seriesAverageCompletionRate":31.86034027579036,"seriesCompletionRate_ios":27.333348301488584,"seriesCompletionRate_android":4.748967127716903,"seriesCompletionRate":16.04153802975021,"started_android":26129,"completed_android":3156,"loveCount":51,"commentCount":9,"sentimentAverage":2.3333333333333335,"sentimentCount":9,"metascore":39.51754326097447,"ACL":{"*":{"read":true},"XcKlOeE3he":{"write":true}},"objectId":"AQZdqyBfrF","__type":"Object","className":"Story"},{"inappropriateContentFlaggers":[],"editedAt":{"__type":"Date","iso":"2018-03-08T23:33:31.830Z"},"searchTerms":["9","b","bo","boy","boyf","boyfr","boyfri","boyfrie","boyfrien","boyfriend","c","cl","cls","clst","clsto","clston","clstone","e","ep","epi","epis","episo","episod","episode","f","fa","fak","fake","m","my","s","st","sto","ston","stone"],"tags":[""],"authors":[{"__type":"Pointer","className":"Author","objectId":"TEKMJMEKyI"}],"characters":[{"__type":"Pointer","className":"Character","objectId":"KcHNlI8KBe"},{"__type":"Pointer","className":"Character","objectId":"7ItxF18qTa"},{"__type":"Pointer","className":"Character","objectId":"Z6kaDUlq5q"},{"__type":"Pointer","className":"Character","objectId":"B73BvmGZCF"},{"__type":"Pointer","className":"Character","objectId":"dQz5nASxdM"}],"authorsObjectIds":["XcKlOeE3he"],"uid":"myfakeboyfriend-9","hidden":false,"title":"My Fake Boyfriend - Episode 9","seriesTitle":"My Fake Boyfriend","lang":"en","canonicalTitle":"my fake boyfriend","storyDescription":"Hazel gets teased by all the boys, but Jack has a secret crush on her…","trackMessage":false,"editorsChoice":false,"teaser":false,"createdOutsideApp":true,"creator":"web-uploader","pendingDeletion":false,"inappropriateContent":false,"seriesTitleAutoGenerated":true,"alreadyPublished":true,"risk":-1,"wordCount":1216,"seriesIdentifier":"0b6b22f3-6d4b-55fd-942a-9653736c8412","category":{"__type":"Pointer","className":"Genre","objectId":"PE8id6J1mi"},"episodeIndex":9,"episodeSeriesName":"Episode 9","episodeTitle":"Episode 9","episodeCount":10,"author":{"autoFolloweesFollowers":[],"username":"CLStone","lastName":"Stone","firstName":"C.L.","fullName":"C.L. Stone","bio":"C. L. Stone likes 🍫 and #findingburiedtreasure. Her books are about 💞 and @dark_themes and #chocolatechippancakes.","profilePictureSmall":{"__type":"File","name":"cbd6628c68064ce76288ae3ae6ecd336_224-small.jpg","url":"https://d3b7s6bg6ueiky.cloudfront.net/cbd6628c68064ce76288ae3ae6ecd336_224-small.jpg"},"profilePictureMedium":{"__type":"File","name":"184ae0bdaaa84c8ac4d69822098612ae_224-medium.jpg","url":"https://d3b7s6bg6ueiky.cloudfront.net/184ae0bdaaa84c8ac4d69822098612ae_224-medium.jpg"},"createdAt":"2017-11-16T20:12:34.814Z","updatedAt":"2018-06-13T20:21:09.883Z","usernameUpdatedAt":{"__type":"Date","iso":"2017-11-16T20:12:34.923Z"},"canonicalUsername":"clstone","writeCount":10,"lastUpdateMetrics":{"__type":"Date","iso":"2018-03-12T14:28:00.232Z"},"followerCount":18,"followingCount":14,"loveCount":0,"readCount":0,"writtenStoryReadingRightsUntil":{"__type":"Date","iso":"2018-11-28T09:44:24.725Z"},"lastNotificationCreatedAt":{"__type":"Date","iso":"2018-06-13T20:21:09.868Z"},"bestSellingBadgeType":"nyt","ACL":{"*":{"read":true},"XcKlOeE3he":{"read":true,"write":true}},"objectId":"XcKlOeE3he","__type":"Object","className":"_User"},"recommendable":false,"searchable":true,"readable":true,"country":"en","genre":"Romance","group":1,"createdAt":"2018-03-02T22:41:39.877Z","updatedAt":"2018-07-04T05:09:07.372Z","aclUpdatedAt":{"__type":"Date","iso":"2018-03-02T22:41:39.915Z"},"lastUpdateMetrics":{"__type":"Date","iso":"2018-07-03T08:54:16.681Z"},"sampleLovers":[],"readCount":14530,"searchTermsUpdatedAt":{"__type":"Date","iso":"2018-07-04T04:55:00.918Z"},"scoreUpdatedAt":{"__type":"Date","iso":"2018-07-04T05:09:00.201Z"},"previousReadVelocity":136,"readVelocity":135,"readAcceleration":-1,"i18n":"fr,es,de,ja,ko,pt,it,ar","style":"{\"theme\":\"imessage\",\"messages\":{\"characterColors\":[\"#A8E7E1\",\"#EDAFCD\",\"#E5CF9F\",\"#CED699\",\"#EDAFCD\"],\"textColors\":[\"#000000\",\"#000000\",\"#000000\",\"#000000\",\"#000000\"]}}","coverImageFile":{"__type":"File","name":"6332999082e1c9e18ffe4701ad18728d_myfakeboyfriend_cover_v3.jpg","url":"https://d3b7s6bg6ueiky.cloudfront.net/6332999082e1c9e18ffe4701ad18728d_myfakeboyfriend_cover_v3.jpg"},"postPaywallNotification":"Hooray 🎉 Hazel is going to Jack’s house to cheer him up! But is the whole thing going to blow up in her face? Tap back into Hooked to find out.","prePaywallNotification":"Wow, Jack and Hazel have REALLY hit a low — but don’t give up on them just yet! Tap back into Hooked to see how she cheers him back up 😃😃","started_ios":12205,"completed_ios":11580,"loveRatio":0.004473503097040606,"commentRatio":0.0004860098590571409,"completionRateUpdatedAt":{"__type":"Date","iso":"2018-07-04T04:30:06.888Z"},"rd_started_ios":3647,"rd_started_android":37197,"rd_completed_ios":3520,"rd_completed_android":841,"completionRate_ios":94.87704918032787,"completionRate_android":6.396084368583694,"rd_completionRate_ios":96.51768576912531,"rd_completionRate_android":2.2609350216415303,"completionRate":24.263038548752835,"seriesAverageCompletionRate_ios":77.9205484637547,"seriesAverageCompletionRate_android":9.975594341484374,"seriesAverageCompletionRate":31.86034027579036,"seriesCompletionRate_ios":27.333348301488584,"seriesCompletionRate_android":4.748967127716903,"seriesCompletionRate":16.04153802975021,"started_android":48220,"completed_android":3085,"loveCount":65,"commentCount":7,"sentimentAverage":2.4285714285714284,"sentimentCount":7,"metascore":35.598777564122614,"ACL":{"*":{"read":true},"XcKlOeE3he":{"write":true}},"objectId":"eoDFDg3xI6","__type":"Object","className":"Story"},{"inappropriateContentFlaggers":[],"editedAt":{"__type":"Date","iso":"2018-03-08T23:33:44.393Z"},"searchTerms":["1","10","b","bo","boy","boyf","boyfr","boyfri","boyfrie","boyfrien","boyfriend","c","cl","cls","clst","clsto","clston","clstone","e","ep","epi","epis","episo","episod","episode","f","fa","fak","fake","m","my","s","st","sto","ston","stone"],"tags":[""],"authors":[{"__type":"Pointer","className":"Author","objectId":"TEKMJMEKyI"}],"characters":[{"__type":"Pointer","className":"Character","objectId":"B8DKuyAy3M"},{"__type":"Pointer","className":"Character","objectId":"kEEpRjhpcp"},{"__type":"Pointer","className":"Character","objectId":"CwvWykDgS4"}],"authorsObjectIds":["XcKlOeE3he"],"uid":"myfakeboyfriend-10","hidden":false,"title":"My Fake Boyfriend - Episode 10","seriesTitle":"My Fake Boyfriend","lang":"en","canonicalTitle":"my fake boyfriend","storyDescription":"Hazel gets teased by all the boys, but Jack has a secret crush on her…","trackMessage":false,"editorsChoice":false,"teaser":false,"createdOutsideApp":true,"creator":"web-uploader","pendingDeletion":false,"inappropriateContent":false,"seriesTitleAutoGenerated":true,"alreadyPublished":true,"risk":-1,"wordCount":829,"seriesIdentifier":"0b6b22f3-6d4b-55fd-942a-9653736c8412","category":{"__type":"Pointer","className":"Genre","objectId":"PE8id6J1mi"},"episodeIndex":10,"episodeSeriesName":"Episode 10","episodeTitle":"Episode 10","episodeCount":10,"author":{"autoFolloweesFollowers":[],"username":"CLStone","lastName":"Stone","firstName":"C.L.","fullName":"C.L. Stone","bio":"C. L. Stone likes 🍫 and #findingburiedtreasure. Her books are about 💞 and @dark_themes and #chocolatechippancakes.","profilePictureSmall":{"__type":"File","name":"cbd6628c68064ce76288ae3ae6ecd336_224-small.jpg","url":"https://d3b7s6bg6ueiky.cloudfront.net/cbd6628c68064ce76288ae3ae6ecd336_224-small.jpg"},"profilePictureMedium":{"__type":"File","name":"184ae0bdaaa84c8ac4d69822098612ae_224-medium.jpg","url":"https://d3b7s6bg6ueiky.cloudfront.net/184ae0bdaaa84c8ac4d69822098612ae_224-medium.jpg"},"createdAt":"2017-11-16T20:12:34.814Z","updatedAt":"2018-06-13T20:21:09.883Z","usernameUpdatedAt":{"__type":"Date","iso":"2017-11-16T20:12:34.923Z"},"canonicalUsername":"clstone","writeCount":10,"lastUpdateMetrics":{"__type":"Date","iso":"2018-03-12T14:28:00.232Z"},"followerCount":18,"followingCount":14,"loveCount":0,"readCount":0,"writtenStoryReadingRightsUntil":{"__type":"Date","iso":"2018-11-28T09:44:24.725Z"},"lastNotificationCreatedAt":{"__type":"Date","iso":"2018-06-13T20:21:09.868Z"},"bestSellingBadgeType":"nyt","ACL":{"*":{"read":true},"XcKlOeE3he":{"read":true,"write":true}},"objectId":"XcKlOeE3he","__type":"Object","className":"_User"},"recommendable":false,"searchable":true,"readable":true,"country":"en","genre":"Romance","group":2,"createdAt":"2018-03-02T22:45:18.658Z","updatedAt":"2018-07-04T05:21:22.518Z","aclUpdatedAt":{"__type":"Date","iso":"2018-03-02T22:45:18.704Z"},"lastUpdateMetrics":{"__type":"Date","iso":"2018-07-03T08:48:07.051Z"},"sampleLovers":[],"readCount":13355,"scoreUpdatedAt":{"__type":"Date","iso":"2018-07-04T05:05:00.119Z"},"previousReadVelocity":118,"readVelocity":120,"readAcceleration":2,"searchTermsUpdatedAt":{"__type":"Date","iso":"2018-07-04T05:00:00.740Z"},"i18n":"fr,es,de,ja,ko,pt,it,ar","style":"{\"theme\":\"imessage\",\"messages\":{\"characterColors\":[\"#A8E7E1\",\"#CED699\",\"#E5CF9F\"],\"textColors\":[\"#000000\",\"#000000\",\"#000000\"]}}","coverImageFile":{"__type":"File","name":"54629946ccd047493e093820f3668a06_myfakeboyfriend_cover_v3.jpg","url":"https://d3b7s6bg6ueiky.cloudfront.net/54629946ccd047493e093820f3668a06_myfakeboyfriend_cover_v3.jpg"},"postPaywallNotification":"😍😍 Jack just admitting that he saw Hazel’s journal...now how’s he gonna respond to it? Tap back into Hooked to find out.","prePaywallNotification":"ICYMI: Hazel LOVES Jack 💗💗 Tap into Hooked for the final episode, and to see how he responds to her big confession.","started_ios":14663,"completed_ios":12182,"loveRatio":0.015949082740546613,"authorPromoURL":"https://www.facebook.com/clstonex/","authorPromoDescription":"C.L. Stone likes 🍫 and #findingburiedtreasure. Her books are about 💞 and @dark_themes and #chocolatechippancakes.","authorPromoCTA":"Follow C.L.","authorPromoImage":{"__type":"File","name":"ce91429d1747a489e2bf2c84a02b6152_StoneCL_Photo.jpg","url":"https://d3b7s6bg6ueiky.cloudfront.net/ce91429d1747a489e2bf2c84a02b6152_StoneCL_Photo.jpg"},"commentRatio":0.0044551838707241566,"completionRateUpdatedAt":{"__type":"Date","iso":"2018-07-04T04:30:06.888Z"},"rd_started_ios":4470,"rd_started_android":23425,"rd_completed_ios":3715,"rd_completed_android":834,"completionRate_ios":83.07062436028659,"completionRate_android":6.600505570639453,"rd_completionRate_ios":83.1096196868009,"rd_completionRate_android":3.560298826040555,"completionRate":30.598740845432353,"seriesAverageCompletionRate_ios":77.9205484637547,"seriesAverageCompletionRate_android":9.975594341484374,"seriesAverageCompletionRate":31.86034027579036,"seriesCompletionRate_ios":27.333348301488584,"seriesCompletionRate_android":4.748967127716903,"seriesCompletionRate":16.04153802975021,"started_android":32044,"completed_android":2116,"loveCount":213,"commentCount":60,"sentimentAverage":2.8214285714285716,"sentimentCount":56,"metascore":46.72565639733536,"ACL":{"*":{"read":true},"XcKlOeE3he":{"write":true}},"objectId":"fhJcO9A580","__type":"Object","className":"Story"}]}}